example_package/__init__.py
example_package/main.py
example_package/print_env.py
example_package/print_text.py
example_package/service_function.py
fajitas_tools/__init__.py
fajitas_tools/big_query.py
fajitas_tools/compute_log.py
fajitas_tools/get_env.py
fajitas_tools/gmail.py
fajitas_tools/google_sheet.py
fajitas_tools/main.py
fajitas_tools-0.0.11.dist-info/LICENSE
fajitas_tools-0.0.11.dist-info/METADATA
fajitas_tools-0.0.11.dist-info/WHEEL
fajitas_tools-0.0.11.dist-info/top_level.txt
fajitas_tools-0.0.11.dist-info/RECORD
