Metadata-Version: 2.1
Name: fajitas_tools
Version: 0.0.11
Summary: This package contains tools that will help me to develop my projects
Author: fajitas30
Author-email: maxime.renac@gmail.com
Classifier: Programming Language :: Python :: 3
Classifier: License :: OSI Approved :: MIT License
Classifier: Operating System :: OS Independent
Requires-Python: >=3.6
License-File: LICENSE
